apollo_openapi/__init__.py
apollo_openapi/api_client.py
apollo_openapi/api_response.py
apollo_openapi/configuration.py
apollo_openapi/exceptions.py
apollo_openapi/py.typed
apollo_openapi/rest.py
apollo_openapi/api/__init__.py
apollo_openapi/api/app_management_api.py
apollo_openapi/api/cluster_management_api.py
apollo_openapi/api/instance_management_api.py
apollo_openapi/api/item_management_api.py
apollo_openapi/api/namespace_branch_management_api.py
apollo_openapi/api/namespace_management_api.py
apollo_openapi/api/organization_management_api.py
apollo_openapi/api/release_management_api.py
apollo_openapi/models/__init__.py
apollo_openapi/models/change.py
apollo_openapi/models/cluster_dto.py
apollo_openapi/models/entity_pair_kv_entity.py
apollo_openapi/models/env_cluster_info.py
apollo_openapi/models/item_change_sets.py
apollo_openapi/models/item_dto.py
apollo_openapi/models/kv_entity.py
apollo_openapi/models/list_item_diffs.py
apollo_openapi/models/list_release_bo.py
apollo_openapi/models/map_string.py
apollo_openapi/models/namespace_gray_del_release_dto.py
apollo_openapi/models/namespace_identifier.py
apollo_openapi/models/namespace_release_dto.py
apollo_openapi/models/namespace_sync_model.py
apollo_openapi/models/namespace_text_model.py
apollo_openapi/models/open_app_dto.py
apollo_openapi/models/open_app_namespace_dto.py
apollo_openapi/models/open_cluster_dto.py
apollo_openapi/models/open_create_app_dto.py
apollo_openapi/models/open_env_cluster_dto.py
apollo_openapi/models/open_gray_release_rule_dto.py
apollo_openapi/models/open_gray_release_rule_item_dto.py
apollo_openapi/models/open_instance_config_dto.py
apollo_openapi/models/open_instance_dto.py
apollo_openapi/models/open_item_dto.py
apollo_openapi/models/open_namespace_dto.py
apollo_openapi/models/open_namespace_lock_dto.py
apollo_openapi/models/open_organization_dto.py
apollo_openapi/models/open_page_dto_open_instance_dto.py
apollo_openapi/models/open_page_dto_open_item_dto.py
apollo_openapi-0.0.1.dist-info/METADATA
apollo_openapi-0.0.1.dist-info/WHEEL
apollo_openapi-0.0.1.dist-info/top_level.txt
apollo_openapi-0.0.1.dist-info/RECORD
